gera2ld/socks/__init__.py
gera2ld/socks/client/__init__.py
gera2ld/socks/client/base.py
gera2ld/socks/client/handler.py
gera2ld/socks/client/socks4.py
gera2ld/socks/client/socks5.py
gera2ld/socks/client/udp.py
gera2ld/socks/server/__init__.py
gera2ld/socks/server/__main__.py
gera2ld/socks/server/base.py
gera2ld/socks/server/config.py
gera2ld/socks/server/socks4.py
gera2ld/socks/server/socks5.py
gera2ld/socks/server/udp.py
gera2ld/socks/utils/__init__.py
gera2ld/socks/utils/base.py
gera2ld/socks/utils/dns.py
gera2ld/socks/utils/error.py
gera2ld/socks/utils/proxy.py
gera2ld/socks/utils/socks4.py
gera2ld/socks/utils/socks5.py
gera2ld/socks/utils/udp.py
gera2ld.socks-0.5.0.dist-info/WHEEL
gera2ld.socks-0.5.0.dist-info/METADATA
gera2ld.socks-0.5.0.dist-info/RECORD
